powersall/__init__.py
powersall/__main__.py
powersall/functions.py
powersall/powersall.py
powersall-2.0.3.dist-info/METADATA
powersall-2.0.3.dist-info/WHEEL
powersall-2.0.3.dist-info/entry_points.txt
powersall-2.0.3.dist-info/licenses/LICENSE
powersall-2.0.3.dist-info/RECORD
