Metadata-Version: 2.4
Name: powersall
Version: 2.0.3
Summary: Advanced Powerball lottery analysis and number generator tool
Project-URL: Homepage, https://github.com/james-see/powersall
Project-URL: Repository, https://github.com/james-see/powersall
Project-URL: Documentation, https://james-see.github.io/powersall
Author-email: James Campbell <james@jamescampbell.us>
License: MIT
License-File: LICENSE
Keywords: analysis,lottery,lotto,megamillions,powerball,random-numbers
Classifier: Development Status :: 4 - Beta
Classifier: Intended Audience :: End Users/Desktop
Classifier: License :: OSI Approved :: MIT License
Classifier: Programming Language :: Python :: 3
Classifier: Programming Language :: Python :: 3.14
Classifier: Topic :: Games/Entertainment
Classifier: Topic :: Utilities
Requires-Python: >=3.11
Requires-Dist: beautifulsoup4>=4.12.0
Requires-Dist: lxml>=4.9.0
Requires-Dist: markovify>=0.9.0
Requires-Dist: matplotlib>=3.8.0
Requires-Dist: numpy>=1.26.0
Requires-Dist: pandas>=2.0.0
Requires-Dist: plotly>=5.17.0
Requires-Dist: requests>=2.31.0
Requires-Dist: streamlit>=1.28.0
